[
  {
    "id": "a60fd1fd-1df5-4748-8fc4-bc3917e1b4c3",
    "title": "Пикник на обочине",
    "author": "Аркадий и Борис Стругацкие",
    "year": 1972,
    "genre": "фантастика",
    "tags": [
      "классика",
      "советская"
    ],
    "isbn": "",
    "pages": 256,
    "quotes": [
      "Счастье для всех, даром..."
    ],
    "added_at": "2025-10-31T09:38:19Z"
  },
  {
    "id": "06a6d969-f66d-4429-ae17-5f937c3a3497",
    "title": "Практика кибербезопасности",
    "author": "Николай Иванов",
    "year": 2020,
    "genre": "научпоп",
    "tags": [
      "ИБ",
      "практика",
      "рекомендовано"
    ],
    "isbn": "9785000000001",
    "pages": 384,
    "quotes": [],
    "added_at": "2025-10-31T09:38:20Z"
  },
  {
    "id": "68c77c05-158e-4a13-8c30-3783f6c67531",
    "title": "Мастер и Маргарита",
    "author": "Михаил Булгаков",
    "year": 1967,
    "genre": "роман",
    "tags": [
      "классика",
      "мистика"
    ],
    "isbn": "",
    "pages": 480,
    "quotes": [],
    "added_at": "2025-10-31T10:28:13Z"
  },
  {
    "id": "3504ae57-d156-4887-a9db-6365c8e5bb0d",
    "title": "Трудно быть богом",
    "author": "Аркадий и Борис Стругацкие",
    "year": 1964,
    "genre": "фантастика",
    "tags": [
      "классика"
    ],
    "isbn": "",
    "pages": 320,
    "quotes": [],
    "added_at": "2025-10-31T10:28:13Z"
  },
  {
    "id": "fd0494ee-2e28-45f7-9f1b-658f7190f8b2",
    "title": "1984",
    "author": "Джордж Оруэлл",
    "year": 1949,
    "genre": "антиутопия",
    "tags": [
      "классика",
      "политика"
    ],
    "isbn": "",
    "pages": 328,
    "quotes": [],
    "added_at": "2025-10-31T10:28:13Z"
  },
  {
    "id": "629c302e-d12e-4bcb-8ab5-2fe076c02f16",
    "title": "Солярис",
    "author": "Станислав Лем",
    "year": 1961,
    "genre": "фантастика",
    "tags": [
      "философия"
    ],
    "isbn": "",
    "pages": 288,
    "quotes": [],
    "added_at": "2025-10-31T10:28:13Z"
  },
  {
    "id": "c82a82a7-8230-4f7f-add5-d71de80c5885",
    "title": "Властелин колец: Братство Кольца",
    "author": "Дж. Р. Р. Толкин",
    "year": 1954,
    "genre": "фэнтези",
    "tags": [
      "эпическое",
      "классика"
    ],
    "isbn": "",
    "pages": 423,
    "quotes": [],
    "added_at": "2025-10-31T10:28:13Z"
  },
  {
    "id": "ee9dbc3c-21a6-4d28-8da2-17ebf9abb8f2",
    "title": "Собачье сердце",
    "author": "Михаил Булгаков",
    "year": 1925,
    "genre": "сатира",
    "tags": [
      "классика"
    ],
    "isbn": "",
    "pages": 192,
    "quotes": [],
    "added_at": "2025-10-31T10:28:14Z"
  },
  {
    "id": "b26ff265-c445-454e-b2a0-99e1c5c57177",
    "title": "Ночной дозор",
    "author": "Сергей Лукьяненко",
    "year": 1998,
    "genre": "фэнтези",
    "tags": [
      "современное",
      "городское"
    ],
    "isbn": "",
    "pages": 384,
    "quotes": [],
    "added_at": "2025-10-31T10:28:14Z"
  },
  {
    "id": "46b1060f-d735-4e9b-90d7-258a7cc0d700",
    "title": "Метро 2033",
    "author": "Дмитрий Глуховский",
    "year": 2005,
    "genre": "постапокалипсис",
    "tags": [
      "фантастика",
      "современное"
    ],
    "isbn": "",
    "pages": 460,
    "quotes": [],
    "added_at": "2025-10-31T10:28:14Z"
  },
  {
    "id": "5b30f91f-8ec2-404c-a33b-f3ef9f684af8",
    "title": "О дивный новый мир",
    "author": "Олдос Хаксли",
    "year": 1932,
    "genre": "антиутопия",
    "tags": [
      "классика"
    ],
    "isbn": "",
    "pages": 288,
    "quotes": [],
    "added_at": "2025-10-31T10:28:14Z"
  },
  {
    "id": "7314473c-db27-4bc1-971e-acf82555bda1",
    "title": "Мы",
    "author": "Евгений Замятин",
    "year": 1920,
    "genre": "антиутопия",
    "tags": [
      "классика",
      "русская"
    ],
    "isbn": "",
    "pages": 224,
    "quotes": [],
    "added_at": "2025-10-31T10:28:14Z"
  },
  {
    "id": "8b896465-4811-4555-9c7d-9931a0f44b8b",
    "title": "Мартин Иден",
    "author": "Джек Лондон",
    "year": 1909,
    "genre": "роман",
    "tags": [
      "классика",
      "самореализация"
    ],
    "isbn": "",
    "pages": 480,
    "quotes": [],
    "added_at": "2025-10-31T10:28:14Z"
  },
  {
    "id": "dad6ed6c-fa40-4468-80fd-15c89eb98b99",
    "title": "Герой нашего времени",
    "author": "Михаил Лермонтов",
    "year": 1840,
    "genre": "роман",
    "tags": [
      "классика",
      "русская"
    ],
    "isbn": "",
    "pages": 256,
    "quotes": [],
    "added_at": "2025-10-31T10:28:14Z"
  },
  {
    "id": "f9407c76-3025-4fa3-8480-f16f2d089fb2",
    "title": "Преступление и наказание",
    "author": "Фёдор Достоевский",
    "year": 1866,
    "genre": "роман",
    "tags": [
      "классика",
      "психология"
    ],
    "isbn": "",
    "pages": 672,
    "quotes": [],
    "added_at": "2025-10-31T10:28:14Z"
  },
  {
    "id": "9c623dd7-81f0-4fba-9150-07ec8e6ba4d8",
    "title": "Анна Каренина",
    "author": "Лев Толстой",
    "year": 1878,
    "genre": "роман",
    "tags": [
      "классика",
      "русская"
    ],
    "isbn": "",
    "pages": 864,
    "quotes": [],
    "added_at": "2025-10-31T10:28:14Z"
  },
  {
    "id": "451aafbf-cf1a-4890-8ce8-31ed54a7f4a3",
    "title": "Три товарища",
    "author": "Эрих Мария Ремарк",
    "year": 1936,
    "genre": "роман",
    "tags": [
      "драма",
      "классика"
    ],
    "isbn": "",
    "pages": 480,
    "quotes": [],
    "added_at": "2025-10-31T10:28:15Z"
  },
  {
    "id": "8f0350b3-0edf-43a6-9600-1bf917db8415",
    "title": "451° по Фаренгейту",
    "author": "Рэй Брэдбери",
    "year": 1953,
    "genre": "фантастика",
    "tags": [
      "антиутопия",
      "классика"
    ],
    "isbn": "",
    "pages": 256,
    "quotes": [],
    "added_at": "2025-10-31T10:28:15Z"
  },
  {
    "id": "567b3a5a-d32a-4fa0-b498-d89c9d800de3",
    "title": "Дюна",
    "author": "Фрэнк Герберт",
    "year": 1965,
    "genre": "фантастика",
    "tags": [
      "космоопера",
      "эпическое"
    ],
    "isbn": "",
    "pages": 688,
    "quotes": [],
    "added_at": "2025-10-31T10:28:15Z"
  },
  {
    "id": "8c66d346-d133-4e9a-81da-a3a932ac259f",
    "title": "Автостопом по галактике",
    "author": "Дуглас Адамс",
    "year": 1979,
    "genre": "фантастика",
    "tags": [
      "юмор"
    ],
    "isbn": "",
    "pages": 224,
    "quotes": [],
    "added_at": "2025-10-31T10:28:15Z"
  },
  {
    "id": "d2f813c2-65ef-40ea-91fb-f8366c6ebfb4",
    "title": "Туманность Андромеды",
    "author": "Иван Ефремов",
    "year": 1957,
    "genre": "фантастика",
    "tags": [
      "советская",
      "классика"
    ],
    "isbn": "",
    "pages": 352,
    "quotes": [],
    "added_at": "2025-10-31T10:28:15Z"
  }
]